[
  {
    "report_id": "PRR81151340",
    "report_type": "Tax Summary",
    "report_period": "2024-12",
    "total_employees": 178,
    "total_salary": 29089678.57,
    "total_deductions": 2431807.27,
    "net_payment": 9289145.29,
    "created_by": "Jose Martin",
    "created_date": "2024-12-17T05:16:09",
    "last_updated": "2024-12-22T05:16:09"
  },
  {
    "report_id": "PRR64664466",
    "report_type": "Deduction Summary",
    "report_period": "2024-06",
    "total_employees": 251,
    "total_salary": 43372016.36,
    "total_deductions": 3346101.97,
    "net_payment": 31327466.46,
    "created_by": "Wesley Chang",
    "created_date": "2024-06-21T17:39:12",
    "last_updated": "2024-06-25T17:39:12"
  },
  {
    "report_id": "PRR88701473",
    "report_type": "Monthly Payroll",
    "report_period": "2024-08",
    "total_employees": 433,
    "total_salary": 28513655.82,
    "total_deductions": 2589746.82,
    "net_payment": 39635624.55,
    "created_by": "Kevin Bush",
    "created_date": "2024-08-24T19:07:12",
    "last_updated": "2024-08-28T19:07:12"
  },
  {
    "report_id": "PRR2239535",
    "report_type": "Deduction Summary",
    "report_period": "2024-06",
    "total_employees": 210,
    "total_salary": 8790634.16,
    "total_deductions": 4660139.68,
    "net_payment": 10316924.83,
    "created_by": "Anthony Palmer",
    "created_date": "2024-06-01T09:50:38",
    "last_updated": "2024-06-02T09:50:38"
  },
  {
    "report_id": "PRR96168587",
    "report_type": "Deduction Summary",
    "report_period": "2024-11",
    "total_employees": 205,
    "total_salary": 23448918.59,
    "total_deductions": 1197790.05,
    "net_payment": 36052397.78,
    "created_by": "Lori Delacruz",
    "created_date": "2024-11-21T01:02:04",
    "last_updated": "2024-11-23T01:02:04"
  },
  {
    "report_id": "PRR14733139",
    "report_type": "Deduction Summary",
    "report_period": "2025-01",
    "total_employees": 365,
    "total_salary": 39419840.4,
    "total_deductions": 4526509.5,
    "net_payment": 39989950.63,
    "created_by": "Autumn Weaver",
    "created_date": "2025-01-06T11:20:50",
    "last_updated": "2025-01-08T11:20:50"
  },
  {
    "report_id": "PRR7393422",
    "report_type": "Tax Summary",
    "report_period": "2024-09",
    "total_employees": 352,
    "total_salary": 21199066.4,
    "total_deductions": 1857080.74,
    "net_payment": 21851877.67,
    "created_by": "Dylan Horton Jr.",
    "created_date": "2024-09-20T04:11:03",
    "last_updated": "2024-09-25T04:11:03"
  },
  {
    "report_id": "PRR59357667",
    "report_type": "Allowance Summary",
    "report_period": "2024-06",
    "total_employees": 482,
    "total_salary": 20450711.2,
    "total_deductions": 1634076.33,
    "net_payment": 33804466.57,
    "created_by": "Christopher Larsen",
    "created_date": "2024-06-05T11:51:42",
    "last_updated": "2024-06-09T11:51:42"
  },
  {
    "report_id": "PRR10074344",
    "report_type": "Tax Summary",
    "report_period": "2024-11",
    "total_employees": 397,
    "total_salary": 45441944.96,
    "total_deductions": 2891966.5,
    "net_payment": 9111546.31,
    "created_by": "Rebecca Davis DVM",
    "created_date": "2024-11-19T07:39:34",
    "last_updated": "2024-11-21T07:39:34"
  },
  {
    "report_id": "PRR66515009",
    "report_type": "Monthly Payroll",
    "report_period": "2025-02",
    "total_employees": 308,
    "total_salary": 20337860.46,
    "total_deductions": 2694787.84,
    "net_payment": 27116849.86,
    "created_by": "Beverly Salinas",
    "created_date": "2025-02-13T21:59:26",
    "last_updated": "2025-02-16T21:59:26"
  },
  {
    "report_id": "PRR5430491",
    "report_type": "Allowance Summary",
    "report_period": "2024-12",
    "total_employees": 100,
    "total_salary": 5804649.28,
    "total_deductions": 3471787.47,
    "net_payment": 18287935.55,
    "created_by": "Heather Frederick",
    "created_date": "2024-12-24T16:03:25",
    "last_updated": "2024-12-27T16:03:25"
  },
  {
    "report_id": "PRR20413395",
    "report_type": "Tax Summary",
    "report_period": "2024-10",
    "total_employees": 120,
    "total_salary": 44131307.83,
    "total_deductions": 1257032.5,
    "net_payment": 23187856.58,
    "created_by": "Tammy Hawkins",
    "created_date": "2024-10-11T11:38:47",
    "last_updated": "2024-10-15T11:38:47"
  },
  {
    "report_id": "PRR18655464",
    "report_type": "Deduction Summary",
    "report_period": "2024-05",
    "total_employees": 452,
    "total_salary": 24250228.28,
    "total_deductions": 4869187.42,
    "net_payment": 12297042.8,
    "created_by": "Charles Burton",
    "created_date": "2024-05-26T17:13:11",
    "last_updated": "2024-05-27T17:13:11"
  },
  {
    "report_id": "PRR71071131",
    "report_type": "Department-wise Summary",
    "report_period": "2025-03",
    "total_employees": 498,
    "total_salary": 14450354.28,
    "total_deductions": 4800297.21,
    "net_payment": 6696860.89,
    "created_by": "Keith West",
    "created_date": "2025-03-06T08:55:49",
    "last_updated": "2025-03-11T08:55:49"
  },
  {
    "report_id": "PRR21975707",
    "report_type": "Monthly Payroll",
    "report_period": "2024-11",
    "total_employees": 493,
    "total_salary": 33507794.1,
    "total_deductions": 1780131.57,
    "net_payment": 10192128.74,
    "created_by": "Nicole Holden",
    "created_date": "2024-11-03T06:42:48",
    "last_updated": "2024-11-06T06:42:48"
  },
  {
    "report_id": "PRR83494386",
    "report_type": "Department-wise Summary",
    "report_period": "2024-09",
    "total_employees": 373,
    "total_salary": 49364237.26,
    "total_deductions": 3593334.47,
    "net_payment": 25528144.1,
    "created_by": "Ethan Chen",
    "created_date": "2024-09-05T03:13:06",
    "last_updated": "2024-09-07T03:13:06"
  },
  {
    "report_id": "PRR38939076",
    "report_type": "Deduction Summary",
    "report_period": "2024-10",
    "total_employees": 408,
    "total_salary": 40978477.99,
    "total_deductions": 3466743.75,
    "net_payment": 40112753.51,
    "created_by": "Christopher Ortega",
    "created_date": "2024-10-19T06:52:57",
    "last_updated": "2024-10-20T06:52:57"
  },
  {
    "report_id": "PRR53355818",
    "report_type": "Allowance Summary",
    "report_period": "2024-09",
    "total_employees": 241,
    "total_salary": 29514583.11,
    "total_deductions": 3959038.66,
    "net_payment": 22759268.18,
    "created_by": "George Lopez",
    "created_date": "2024-09-14T03:40:54",
    "last_updated": "2024-09-17T03:40:54"
  },
  {
    "report_id": "PRR75731302",
    "report_type": "Monthly Payroll",
    "report_period": "2024-08",
    "total_employees": 386,
    "total_salary": 32602763.63,
    "total_deductions": 2424015.36,
    "net_payment": 41049874.41,
    "created_by": "Ashley Martinez",
    "created_date": "2024-08-04T08:07:07",
    "last_updated": "2024-08-05T08:07:07"
  },
  {
    "report_id": "PRR48819447",
    "report_type": "Allowance Summary",
    "report_period": "2024-04",
    "total_employees": 416,
    "total_salary": 19618370.78,
    "total_deductions": 1115930.15,
    "net_payment": 40152548.92,
    "created_by": "Connie Price",
    "created_date": "2024-04-11T08:44:45",
    "last_updated": "2024-04-12T08:44:45"
  },
  {
    "report_id": "PRR2948070",
    "report_type": "Deduction Summary",
    "report_period": "2024-12",
    "total_employees": 463,
    "total_salary": 40192265.53,
    "total_deductions": 3703588.28,
    "net_payment": 30157492.76,
    "created_by": "Ashley Cabrera",
    "created_date": "2024-12-31T01:24:37",
    "last_updated": "2025-01-02T01:24:37"
  },
  {
    "report_id": "PRR31169466",
    "report_type": "Monthly Payroll",
    "report_period": "2024-04",
    "total_employees": 413,
    "total_salary": 44268592.2,
    "total_deductions": 4585694.1,
    "net_payment": 15891923.36,
    "created_by": "Connie Freeman",
    "created_date": "2024-04-24T17:18:00",
    "last_updated": "2024-04-28T17:18:00"
  },
  {
    "report_id": "PRR27345579",
    "report_type": "Monthly Payroll",
    "report_period": "2025-03",
    "total_employees": 252,
    "total_salary": 20026787.78,
    "total_deductions": 1452554.86,
    "net_payment": 31751666.81,
    "created_by": "Thomas Davis",
    "created_date": "2025-03-21T11:44:03",
    "last_updated": "2025-03-24T11:44:03"
  },
  {
    "report_id": "PRR16263897",
    "report_type": "Allowance Summary",
    "report_period": "2025-02",
    "total_employees": 107,
    "total_salary": 5346114.31,
    "total_deductions": 1173581.09,
    "net_payment": 16444707.79,
    "created_by": "Lori Davis",
    "created_date": "2025-02-10T10:12:20",
    "last_updated": "2025-02-13T10:12:20"
  },
  {
    "report_id": "PRR83541449",
    "report_type": "Department-wise Summary",
    "report_period": "2024-09",
    "total_employees": 103,
    "total_salary": 23704485.46,
    "total_deductions": 1137709.13,
    "net_payment": 39872560.86,
    "created_by": "Gail Bishop",
    "created_date": "2024-09-30T05:22:50",
    "last_updated": "2024-10-05T05:22:50"
  },
  {
    "report_id": "PRR41505251",
    "report_type": "Tax Summary",
    "report_period": "2024-06",
    "total_employees": 140,
    "total_salary": 49878578.0,
    "total_deductions": 4079857.03,
    "net_payment": 37710602.51,
    "created_by": "Michael Wilkins",
    "created_date": "2024-06-16T12:41:05",
    "last_updated": "2024-06-18T12:41:05"
  },
  {
    "report_id": "PRR23273859",
    "report_type": "Monthly Payroll",
    "report_period": "2024-07",
    "total_employees": 351,
    "total_salary": 10721692.41,
    "total_deductions": 1142297.41,
    "net_payment": 28824081.53,
    "created_by": "Crystal Hernandez",
    "created_date": "2024-07-22T04:17:49",
    "last_updated": "2024-07-27T04:17:49"
  },
  {
    "report_id": "PRR31418728",
    "report_type": "Deduction Summary",
    "report_period": "2024-11",
    "total_employees": 234,
    "total_salary": 14736939.45,
    "total_deductions": 4932960.01,
    "net_payment": 22560103.94,
    "created_by": "Russell Bright",
    "created_date": "2024-11-25T13:45:05",
    "last_updated": "2024-11-29T13:45:05"
  },
  {
    "report_id": "PRR14588240",
    "report_type": "Department-wise Summary",
    "report_period": "2024-06",
    "total_employees": 250,
    "total_salary": 14147510.52,
    "total_deductions": 4755165.39,
    "net_payment": 21250899.17,
    "created_by": "Holly Wiley",
    "created_date": "2024-06-17T06:37:48",
    "last_updated": "2024-06-19T06:37:48"
  },
  {
    "report_id": "PRR81647929",
    "report_type": "Department-wise Summary",
    "report_period": "2024-11",
    "total_employees": 273,
    "total_salary": 36266716.79,
    "total_deductions": 1836960.3,
    "net_payment": 33706352.8,
    "created_by": "Alexander Wagner",
    "created_date": "2024-11-21T08:44:33",
    "last_updated": "2024-11-24T08:44:33"
  },
  {
    "report_id": "PRR4991655",
    "report_type": "Department-wise Summary",
    "report_period": "2024-05",
    "total_employees": 137,
    "total_salary": 17004784.19,
    "total_deductions": 3253917.67,
    "net_payment": 10752963.05,
    "created_by": "Kelly Miller",
    "created_date": "2024-05-01T11:31:47",
    "last_updated": "2024-05-02T11:31:47"
  },
  {
    "report_id": "PRR93986387",
    "report_type": "Deduction Summary",
    "report_period": "2024-06",
    "total_employees": 249,
    "total_salary": 8733539.35,
    "total_deductions": 1065911.8,
    "net_payment": 14270969.7,
    "created_by": "Jodi Hodges",
    "created_date": "2024-06-03T18:06:24",
    "last_updated": "2024-06-08T18:06:24"
  },
  {
    "report_id": "PRR29577252",
    "report_type": "Deduction Summary",
    "report_period": "2024-08",
    "total_employees": 108,
    "total_salary": 24265306.88,
    "total_deductions": 4765307.89,
    "net_payment": 39947741.16,
    "created_by": "Phillip Austin",
    "created_date": "2024-08-15T01:31:09",
    "last_updated": "2024-08-20T01:31:09"
  },
  {
    "report_id": "PRR71775691",
    "report_type": "Allowance Summary",
    "report_period": "2024-12",
    "total_employees": 326,
    "total_salary": 12666853.81,
    "total_deductions": 2367304.02,
    "net_payment": 27067493.61,
    "created_by": "Katie Myers",
    "created_date": "2024-12-14T06:13:01",
    "last_updated": "2024-12-17T06:13:01"
  },
  {
    "report_id": "PRR1270390",
    "report_type": "Deduction Summary",
    "report_period": "2024-08",
    "total_employees": 485,
    "total_salary": 7262986.04,
    "total_deductions": 3353419.13,
    "net_payment": 26530733.48,
    "created_by": "Rebekah Sutton",
    "created_date": "2024-08-04T06:36:04",
    "last_updated": "2024-08-06T06:36:04"
  },
  {
    "report_id": "PRR91108146",
    "report_type": "Deduction Summary",
    "report_period": "2024-12",
    "total_employees": 283,
    "total_salary": 7860221.94,
    "total_deductions": 1281940.9,
    "net_payment": 7982852.86,
    "created_by": "John Campbell",
    "created_date": "2024-12-14T18:59:17",
    "last_updated": "2024-12-19T18:59:17"
  },
  {
    "report_id": "PRR94370941",
    "report_type": "Deduction Summary",
    "report_period": "2024-08",
    "total_employees": 178,
    "total_salary": 36489550.59,
    "total_deductions": 3015254.41,
    "net_payment": 39200773.39,
    "created_by": "Tracy Zimmerman",
    "created_date": "2024-08-19T16:07:33",
    "last_updated": "2024-08-24T16:07:33"
  },
  {
    "report_id": "PRR18831079",
    "report_type": "Allowance Summary",
    "report_period": "2024-04",
    "total_employees": 474,
    "total_salary": 45781885.19,
    "total_deductions": 4802741.74,
    "net_payment": 25407307.67,
    "created_by": "Sheryl Cook",
    "created_date": "2024-04-22T10:11:57",
    "last_updated": "2024-04-23T10:11:57"
  },
  {
    "report_id": "PRR63824550",
    "report_type": "Department-wise Summary",
    "report_period": "2024-09",
    "total_employees": 354,
    "total_salary": 21990344.05,
    "total_deductions": 1478946.11,
    "net_payment": 15946610.51,
    "created_by": "Sarah Davis",
    "created_date": "2024-09-30T10:21:15",
    "last_updated": "2024-10-01T10:21:15"
  },
  {
    "report_id": "PRR6362276",
    "report_type": "Deduction Summary",
    "report_period": "2024-12",
    "total_employees": 452,
    "total_salary": 10854649.37,
    "total_deductions": 821996.83,
    "net_payment": 29512956.19,
    "created_by": "John Stevens",
    "created_date": "2024-12-30T09:27:54",
    "last_updated": "2025-01-03T09:27:54"
  },
  {
    "report_id": "PRR81383683",
    "report_type": "Tax Summary",
    "report_period": "2024-11",
    "total_employees": 405,
    "total_salary": 14713197.09,
    "total_deductions": 541243.92,
    "net_payment": 36586065.7,
    "created_by": "Dr. Joshua Collins MD",
    "created_date": "2024-11-04T06:31:21",
    "last_updated": "2024-11-07T06:31:21"
  },
  {
    "report_id": "PRR43133856",
    "report_type": "Allowance Summary",
    "report_period": "2024-09",
    "total_employees": 145,
    "total_salary": 13133107.96,
    "total_deductions": 3351439.87,
    "net_payment": 13569799.28,
    "created_by": "Laura Morgan",
    "created_date": "2024-09-25T13:15:08",
    "last_updated": "2024-09-29T13:15:08"
  },
  {
    "report_id": "PRR60629219",
    "report_type": "Deduction Summary",
    "report_period": "2024-06",
    "total_employees": 146,
    "total_salary": 24417107.13,
    "total_deductions": 4068464.81,
    "net_payment": 6193555.36,
    "created_by": "Patrick Maxwell",
    "created_date": "2024-06-19T08:35:48",
    "last_updated": "2024-06-21T08:35:48"
  },
  {
    "report_id": "PRR68969389",
    "report_type": "Tax Summary",
    "report_period": "2024-11",
    "total_employees": 441,
    "total_salary": 13162069.61,
    "total_deductions": 2664658.57,
    "net_payment": 33811823.71,
    "created_by": "Anthony Ferrell",
    "created_date": "2024-11-04T07:42:48",
    "last_updated": "2024-11-07T07:42:48"
  },
  {
    "report_id": "PRR37466694",
    "report_type": "Department-wise Summary",
    "report_period": "2024-04",
    "total_employees": 181,
    "total_salary": 11217682.03,
    "total_deductions": 1484629.74,
    "net_payment": 11668957.26,
    "created_by": "Robin Glenn",
    "created_date": "2024-04-01T10:51:44",
    "last_updated": "2024-04-02T10:51:44"
  },
  {
    "report_id": "PRR88909043",
    "report_type": "Monthly Payroll",
    "report_period": "2024-12",
    "total_employees": 325,
    "total_salary": 12742824.95,
    "total_deductions": 4811649.93,
    "net_payment": 15854045.9,
    "created_by": "Thomas Smith",
    "created_date": "2024-12-15T06:52:25",
    "last_updated": "2024-12-17T06:52:25"
  },
  {
    "report_id": "PRR6016208",
    "report_type": "Monthly Payroll",
    "report_period": "2024-12",
    "total_employees": 414,
    "total_salary": 6550793.83,
    "total_deductions": 1619542.98,
    "net_payment": 11716895.35,
    "created_by": "Kimberly Rogers",
    "created_date": "2024-12-01T02:22:52",
    "last_updated": "2024-12-04T02:22:52"
  },
  {
    "report_id": "PRR12985808",
    "report_type": "Tax Summary",
    "report_period": "2024-04",
    "total_employees": 321,
    "total_salary": 19912957.32,
    "total_deductions": 1891726.4,
    "net_payment": 4831136.43,
    "created_by": "Chad Williams",
    "created_date": "2024-04-24T12:00:25",
    "last_updated": "2024-04-26T12:00:25"
  },
  {
    "report_id": "PRR13317948",
    "report_type": "Tax Summary",
    "report_period": "2024-10",
    "total_employees": 452,
    "total_salary": 15731105.6,
    "total_deductions": 2160340.95,
    "net_payment": 12653977.96,
    "created_by": "Cody Clark",
    "created_date": "2024-10-21T00:41:15",
    "last_updated": "2024-10-22T00:41:15"
  },
  {
    "report_id": "PRR78654618",
    "report_type": "Monthly Payroll",
    "report_period": "2024-08",
    "total_employees": 383,
    "total_salary": 5470239.68,
    "total_deductions": 4444038.64,
    "net_payment": 29911996.62,
    "created_by": "Juan Perez",
    "created_date": "2024-08-02T22:33:20",
    "last_updated": "2024-08-03T22:33:20"
  },
  {
    "report_id": "PRR67249060",
    "report_type": "Monthly Payroll",
    "report_period": "2024-05",
    "total_employees": 384,
    "total_salary": 36849160.38,
    "total_deductions": 742383.87,
    "net_payment": 28564472.77,
    "created_by": "James Roberts",
    "created_date": "2024-05-30T11:07:38",
    "last_updated": "2024-05-31T11:07:38"
  },
  {
    "report_id": "PRR55613836",
    "report_type": "Deduction Summary",
    "report_period": "2024-11",
    "total_employees": 221,
    "total_salary": 14433482.66,
    "total_deductions": 4860703.91,
    "net_payment": 29995409.24,
    "created_by": "Angela Carlson",
    "created_date": "2024-11-04T14:51:05",
    "last_updated": "2024-11-06T14:51:05"
  },
  {
    "report_id": "PRR74307731",
    "report_type": "Allowance Summary",
    "report_period": "2024-10",
    "total_employees": 136,
    "total_salary": 16501244.47,
    "total_deductions": 4326753.85,
    "net_payment": 39965691.8,
    "created_by": "Matthew Patterson",
    "created_date": "2024-10-10T21:09:39",
    "last_updated": "2024-10-13T21:09:39"
  },
  {
    "report_id": "PRR52888801",
    "report_type": "Department-wise Summary",
    "report_period": "2024-11",
    "total_employees": 453,
    "total_salary": 26069207.92,
    "total_deductions": 909339.37,
    "net_payment": 29268792.69,
    "created_by": "Gabriel Thompson",
    "created_date": "2024-11-11T17:04:48",
    "last_updated": "2024-11-14T17:04:48"
  },
  {
    "report_id": "PRR90555788",
    "report_type": "Monthly Payroll",
    "report_period": "2024-06",
    "total_employees": 128,
    "total_salary": 26131793.45,
    "total_deductions": 3733226.74,
    "net_payment": 7362642.02,
    "created_by": "Matthew Middleton",
    "created_date": "2024-06-17T21:57:40",
    "last_updated": "2024-06-21T21:57:40"
  },
  {
    "report_id": "PRR1645484",
    "report_type": "Monthly Payroll",
    "report_period": "2024-08",
    "total_employees": 280,
    "total_salary": 48231454.12,
    "total_deductions": 3238451.0,
    "net_payment": 16434241.47,
    "created_by": "Brian Strickland",
    "created_date": "2024-08-23T19:58:17",
    "last_updated": "2024-08-27T19:58:17"
  },
  {
    "report_id": "PRR25677887",
    "report_type": "Allowance Summary",
    "report_period": "2025-02",
    "total_employees": 318,
    "total_salary": 22194972.96,
    "total_deductions": 4588029.46,
    "net_payment": 5134512.48,
    "created_by": "Trevor Perez",
    "created_date": "2025-02-08T03:13:03",
    "last_updated": "2025-02-09T03:13:03"
  },
  {
    "report_id": "PRR85188832",
    "report_type": "Deduction Summary",
    "report_period": "2025-01",
    "total_employees": 163,
    "total_salary": 12520240.77,
    "total_deductions": 2762895.43,
    "net_payment": 42512782.73,
    "created_by": "Angela Romero",
    "created_date": "2025-01-21T13:23:55",
    "last_updated": "2025-01-25T13:23:55"
  },
  {
    "report_id": "PRR63684035",
    "report_type": "Tax Summary",
    "report_period": "2024-08",
    "total_employees": 443,
    "total_salary": 36492488.36,
    "total_deductions": 2204952.72,
    "net_payment": 4648268.34,
    "created_by": "Erica Young",
    "created_date": "2024-08-07T12:10:05",
    "last_updated": "2024-08-12T12:10:05"
  },
  {
    "report_id": "PRR92685046",
    "report_type": "Allowance Summary",
    "report_period": "2025-02",
    "total_employees": 487,
    "total_salary": 12468452.91,
    "total_deductions": 2969348.39,
    "net_payment": 14195080.3,
    "created_by": "Dana Smith",
    "created_date": "2025-02-15T14:46:16",
    "last_updated": "2025-02-16T14:46:16"
  },
  {
    "report_id": "PRR83549303",
    "report_type": "Allowance Summary",
    "report_period": "2024-11",
    "total_employees": 480,
    "total_salary": 47922010.84,
    "total_deductions": 1782667.87,
    "net_payment": 19776421.36,
    "created_by": "Brendan Reyes",
    "created_date": "2024-11-18T20:31:12",
    "last_updated": "2024-11-19T20:31:12"
  },
  {
    "report_id": "PRR51628517",
    "report_type": "Department-wise Summary",
    "report_period": "2024-05",
    "total_employees": 131,
    "total_salary": 17357874.16,
    "total_deductions": 2438346.48,
    "net_payment": 6186320.85,
    "created_by": "Christopher Hernandez",
    "created_date": "2024-05-13T06:33:53",
    "last_updated": "2024-05-18T06:33:53"
  },
  {
    "report_id": "PRR26835836",
    "report_type": "Tax Summary",
    "report_period": "2024-03",
    "total_employees": 315,
    "total_salary": 20184674.91,
    "total_deductions": 2488162.08,
    "net_payment": 7414024.77,
    "created_by": "William Holt",
    "created_date": "2024-03-29T10:59:18",
    "last_updated": "2024-03-30T10:59:18"
  },
  {
    "report_id": "PRR92000945",
    "report_type": "Department-wise Summary",
    "report_period": "2024-05",
    "total_employees": 351,
    "total_salary": 14194124.93,
    "total_deductions": 3073037.98,
    "net_payment": 28829953.73,
    "created_by": "Ethan White",
    "created_date": "2024-05-23T18:53:36",
    "last_updated": "2024-05-28T18:53:36"
  },
  {
    "report_id": "PRR67878007",
    "report_type": "Deduction Summary",
    "report_period": "2024-11",
    "total_employees": 124,
    "total_salary": 14466871.86,
    "total_deductions": 4544619.43,
    "net_payment": 35898532.49,
    "created_by": "Caleb Miller",
    "created_date": "2024-11-17T14:20:26",
    "last_updated": "2024-11-22T14:20:26"
  },
  {
    "report_id": "PRR65762359",
    "report_type": "Deduction Summary",
    "report_period": "2024-09",
    "total_employees": 490,
    "total_salary": 39159163.01,
    "total_deductions": 2656748.01,
    "net_payment": 41587179.2,
    "created_by": "Amy Hernandez",
    "created_date": "2024-09-27T10:52:11",
    "last_updated": "2024-10-01T10:52:11"
  },
  {
    "report_id": "PRR93992169",
    "report_type": "Deduction Summary",
    "report_period": "2024-07",
    "total_employees": 423,
    "total_salary": 6863389.32,
    "total_deductions": 3464704.12,
    "net_payment": 34743318.0,
    "created_by": "Robert Eaton",
    "created_date": "2024-07-03T02:45:25",
    "last_updated": "2024-07-07T02:45:25"
  },
  {
    "report_id": "PRR77655113",
    "report_type": "Department-wise Summary",
    "report_period": "2024-08",
    "total_employees": 120,
    "total_salary": 46048804.82,
    "total_deductions": 3050896.94,
    "net_payment": 36317859.3,
    "created_by": "Gabriella Parker",
    "created_date": "2024-08-27T21:48:46",
    "last_updated": "2024-08-31T21:48:46"
  },
  {
    "report_id": "PRR99622475",
    "report_type": "Department-wise Summary",
    "report_period": "2025-02",
    "total_employees": 157,
    "total_salary": 20701738.07,
    "total_deductions": 1244492.03,
    "net_payment": 17242457.01,
    "created_by": "Charlene Romero MD",
    "created_date": "2025-02-20T01:50:30",
    "last_updated": "2025-02-25T01:50:30"
  },
  {
    "report_id": "PRR8274894",
    "report_type": "Allowance Summary",
    "report_period": "2025-02",
    "total_employees": 146,
    "total_salary": 43309382.92,
    "total_deductions": 3345265.67,
    "net_payment": 13648001.63,
    "created_by": "Kelly Bowers",
    "created_date": "2025-02-13T20:26:52",
    "last_updated": "2025-02-17T20:26:52"
  },
  {
    "report_id": "PRR76506122",
    "report_type": "Tax Summary",
    "report_period": "2024-04",
    "total_employees": 371,
    "total_salary": 49070509.47,
    "total_deductions": 4695008.21,
    "net_payment": 42504006.44,
    "created_by": "Susan Price",
    "created_date": "2024-04-10T15:49:14",
    "last_updated": "2024-04-14T15:49:14"
  },
  {
    "report_id": "PRR5557246",
    "report_type": "Tax Summary",
    "report_period": "2024-06",
    "total_employees": 479,
    "total_salary": 35182921.21,
    "total_deductions": 539458.99,
    "net_payment": 21746681.03,
    "created_by": "Tina Robbins",
    "created_date": "2024-06-28T06:37:06",
    "last_updated": "2024-07-01T06:37:06"
  },
  {
    "report_id": "PRR64218419",
    "report_type": "Allowance Summary",
    "report_period": "2024-10",
    "total_employees": 291,
    "total_salary": 11497105.51,
    "total_deductions": 780473.2,
    "net_payment": 43350323.12,
    "created_by": "Daniel Murray",
    "created_date": "2024-10-31T00:09:40",
    "last_updated": "2024-11-04T00:09:40"
  },
  {
    "report_id": "PRR97758280",
    "report_type": "Allowance Summary",
    "report_period": "2024-12",
    "total_employees": 284,
    "total_salary": 43306954.76,
    "total_deductions": 2672721.64,
    "net_payment": 42267076.48,
    "created_by": "Brian Garcia",
    "created_date": "2024-12-25T12:42:00",
    "last_updated": "2024-12-26T12:42:00"
  },
  {
    "report_id": "PRR21181624",
    "report_type": "Monthly Payroll",
    "report_period": "2024-09",
    "total_employees": 212,
    "total_salary": 23394537.79,
    "total_deductions": 3929273.33,
    "net_payment": 10956083.25,
    "created_by": "Donald Mckenzie",
    "created_date": "2024-09-24T03:23:24",
    "last_updated": "2024-09-26T03:23:24"
  },
  {
    "report_id": "PRR40077373",
    "report_type": "Department-wise Summary",
    "report_period": "2024-10",
    "total_employees": 264,
    "total_salary": 44270642.44,
    "total_deductions": 2715757.4,
    "net_payment": 31477462.49,
    "created_by": "Bridget Alvarado DVM",
    "created_date": "2024-10-31T22:27:05",
    "last_updated": "2024-11-05T22:27:05"
  },
  {
    "report_id": "PRR97009433",
    "report_type": "Monthly Payroll",
    "report_period": "2024-04",
    "total_employees": 291,
    "total_salary": 12310903.66,
    "total_deductions": 4014867.98,
    "net_payment": 4883206.09,
    "created_by": "Andrew Monroe",
    "created_date": "2024-04-28T16:00:07",
    "last_updated": "2024-04-30T16:00:07"
  },
  {
    "report_id": "PRR63622536",
    "report_type": "Department-wise Summary",
    "report_period": "2024-12",
    "total_employees": 496,
    "total_salary": 48893319.12,
    "total_deductions": 3448598.61,
    "net_payment": 29201005.32,
    "created_by": "Austin Scott",
    "created_date": "2024-12-18T07:32:04",
    "last_updated": "2024-12-22T07:32:04"
  },
  {
    "report_id": "PRR9617278",
    "report_type": "Tax Summary",
    "report_period": "2024-06",
    "total_employees": 241,
    "total_salary": 41630223.75,
    "total_deductions": 1421610.14,
    "net_payment": 36714996.81,
    "created_by": "Julie Zamora",
    "created_date": "2024-06-24T06:09:31",
    "last_updated": "2024-06-25T06:09:31"
  },
  {
    "report_id": "PRR31475681",
    "report_type": "Deduction Summary",
    "report_period": "2025-02",
    "total_employees": 185,
    "total_salary": 48512784.84,
    "total_deductions": 1363263.28,
    "net_payment": 34784582.74,
    "created_by": "Amy Jones",
    "created_date": "2025-02-09T12:57:45",
    "last_updated": "2025-02-14T12:57:45"
  },
  {
    "report_id": "PRR87232866",
    "report_type": "Deduction Summary",
    "report_period": "2025-03",
    "total_employees": 486,
    "total_salary": 13886073.71,
    "total_deductions": 3876680.87,
    "net_payment": 19986634.15,
    "created_by": "Melissa Estrada",
    "created_date": "2025-03-01T01:38:19",
    "last_updated": "2025-03-04T01:38:19"
  },
  {
    "report_id": "PRR52359845",
    "report_type": "Allowance Summary",
    "report_period": "2024-04",
    "total_employees": 329,
    "total_salary": 49116959.93,
    "total_deductions": 2507025.02,
    "net_payment": 22027277.19,
    "created_by": "William Rodriguez",
    "created_date": "2024-04-07T07:33:58",
    "last_updated": "2024-04-09T07:33:58"
  },
  {
    "report_id": "PRR74935356",
    "report_type": "Allowance Summary",
    "report_period": "2024-04",
    "total_employees": 448,
    "total_salary": 48491816.15,
    "total_deductions": 1219578.81,
    "net_payment": 26895004.97,
    "created_by": "Lauren Bishop",
    "created_date": "2024-04-04T16:58:02",
    "last_updated": "2024-04-08T16:58:02"
  },
  {
    "report_id": "PRR23225973",
    "report_type": "Monthly Payroll",
    "report_period": "2024-07",
    "total_employees": 474,
    "total_salary": 45831195.73,
    "total_deductions": 3177273.81,
    "net_payment": 27674221.87,
    "created_by": "Derek Young",
    "created_date": "2024-07-15T20:51:48",
    "last_updated": "2024-07-19T20:51:48"
  },
  {
    "report_id": "PRR81333538",
    "report_type": "Deduction Summary",
    "report_period": "2024-12",
    "total_employees": 415,
    "total_salary": 6944120.13,
    "total_deductions": 2327279.38,
    "net_payment": 38756894.75,
    "created_by": "Jon Fry",
    "created_date": "2024-12-05T10:48:19",
    "last_updated": "2024-12-09T10:48:19"
  },
  {
    "report_id": "PRR85404985",
    "report_type": "Monthly Payroll",
    "report_period": "2024-05",
    "total_employees": 416,
    "total_salary": 39764430.38,
    "total_deductions": 983128.69,
    "net_payment": 29125137.57,
    "created_by": "Matthew Perry",
    "created_date": "2024-05-29T19:55:07",
    "last_updated": "2024-06-03T19:55:07"
  },
  {
    "report_id": "PRR66217306",
    "report_type": "Department-wise Summary",
    "report_period": "2024-05",
    "total_employees": 170,
    "total_salary": 25573283.53,
    "total_deductions": 1954995.28,
    "net_payment": 28942354.93,
    "created_by": "John Wolfe",
    "created_date": "2024-05-15T07:12:28",
    "last_updated": "2024-05-19T07:12:28"
  },
  {
    "report_id": "PRR5005538",
    "report_type": "Monthly Payroll",
    "report_period": "2025-01",
    "total_employees": 268,
    "total_salary": 41132451.89,
    "total_deductions": 2972994.85,
    "net_payment": 13067577.39,
    "created_by": "Calvin Jones",
    "created_date": "2025-01-08T20:52:51",
    "last_updated": "2025-01-13T20:52:51"
  },
  {
    "report_id": "PRR92176712",
    "report_type": "Tax Summary",
    "report_period": "2024-08",
    "total_employees": 484,
    "total_salary": 23111750.32,
    "total_deductions": 2726995.22,
    "net_payment": 30879640.72,
    "created_by": "Joe Williams",
    "created_date": "2024-08-26T10:31:51",
    "last_updated": "2024-08-27T10:31:51"
  },
  {
    "report_id": "PRR52285305",
    "report_type": "Monthly Payroll",
    "report_period": "2024-05",
    "total_employees": 385,
    "total_salary": 34177369.28,
    "total_deductions": 3405650.61,
    "net_payment": 20448120.46,
    "created_by": "Latoya Chapman",
    "created_date": "2024-05-03T04:04:42",
    "last_updated": "2024-05-07T04:04:42"
  },
  {
    "report_id": "PRR60228424",
    "report_type": "Tax Summary",
    "report_period": "2025-03",
    "total_employees": 386,
    "total_salary": 33843139.93,
    "total_deductions": 3010501.36,
    "net_payment": 4684833.19,
    "created_by": "Christopher Cortez",
    "created_date": "2025-03-20T19:10:13",
    "last_updated": "2025-03-23T19:10:13"
  },
  {
    "report_id": "PRR68512417",
    "report_type": "Tax Summary",
    "report_period": "2025-02",
    "total_employees": 276,
    "total_salary": 9585858.47,
    "total_deductions": 3597464.67,
    "net_payment": 10938587.42,
    "created_by": "Amber Wood",
    "created_date": "2025-02-19T02:55:24",
    "last_updated": "2025-02-23T02:55:24"
  },
  {
    "report_id": "PRR17081414",
    "report_type": "Deduction Summary",
    "report_period": "2024-08",
    "total_employees": 228,
    "total_salary": 47885279.32,
    "total_deductions": 894198.42,
    "net_payment": 36687101.27,
    "created_by": "Thomas Barber",
    "created_date": "2024-08-18T04:42:55",
    "last_updated": "2024-08-23T04:42:55"
  },
  {
    "report_id": "PRR41623510",
    "report_type": "Deduction Summary",
    "report_period": "2025-02",
    "total_employees": 415,
    "total_salary": 34403768.72,
    "total_deductions": 4981921.75,
    "net_payment": 16238001.75,
    "created_by": "James Martinez",
    "created_date": "2025-02-15T17:10:22",
    "last_updated": "2025-02-17T17:10:22"
  },
  {
    "report_id": "PRR72930669",
    "report_type": "Monthly Payroll",
    "report_period": "2024-12",
    "total_employees": 211,
    "total_salary": 33039310.25,
    "total_deductions": 2151645.19,
    "net_payment": 24393580.34,
    "created_by": "Kimberly Trujillo",
    "created_date": "2024-12-27T18:30:10",
    "last_updated": "2024-12-28T18:30:10"
  },
  {
    "report_id": "PRR94151873",
    "report_type": "Deduction Summary",
    "report_period": "2024-10",
    "total_employees": 358,
    "total_salary": 31763791.02,
    "total_deductions": 1662672.82,
    "net_payment": 32003071.43,
    "created_by": "Heather Nichols",
    "created_date": "2024-10-27T10:32:00",
    "last_updated": "2024-11-01T10:32:00"
  },
  {
    "report_id": "PRR46488287",
    "report_type": "Deduction Summary",
    "report_period": "2024-05",
    "total_employees": 488,
    "total_salary": 47903864.01,
    "total_deductions": 989797.94,
    "net_payment": 31848388.08,
    "created_by": "Jennifer Hughes",
    "created_date": "2024-05-23T13:55:41",
    "last_updated": "2024-05-27T13:55:41"
  },
  {
    "report_id": "PRR3129150",
    "report_type": "Department-wise Summary",
    "report_period": "2024-11",
    "total_employees": 361,
    "total_salary": 32049971.74,
    "total_deductions": 3727398.08,
    "net_payment": 25135381.24,
    "created_by": "Karina Schwartz",
    "created_date": "2024-11-02T17:53:04",
    "last_updated": "2024-11-03T17:53:04"
  },
  {
    "report_id": "PRR79389561",
    "report_type": "Monthly Payroll",
    "report_period": "2024-11",
    "total_employees": 127,
    "total_salary": 34661424.73,
    "total_deductions": 4997175.2,
    "net_payment": 43455501.44,
    "created_by": "Kim Allen",
    "created_date": "2024-11-05T12:19:54",
    "last_updated": "2024-11-10T12:19:54"
  },
  {
    "report_id": "PRR40017730",
    "report_type": "Department-wise Summary",
    "report_period": "2024-04",
    "total_employees": 107,
    "total_salary": 10446204.1,
    "total_deductions": 3963482.87,
    "net_payment": 11829603.82,
    "created_by": "Amanda Walters",
    "created_date": "2024-04-05T22:40:44",
    "last_updated": "2024-04-10T22:40:44"
  }
]